LICENSE
MANIFEST.in
README.md
package.json
setup.py
dash_useful_components/CheckBoxTree.py
dash_useful_components/CollapsibleTableBody.py
dash_useful_components/CollapsibleTableCell.py
dash_useful_components/TreeTable.py
dash_useful_components/__init__.py
dash_useful_components/_imports_.py
dash_useful_components/dash_useful_components.min.js
dash_useful_components/dash_useful_components.min.js.map
dash_useful_components/metadata.json
dash_useful_components/package-info.json
dash_useful_components/treetable.css
dash_useful_components.egg-info/PKG-INFO
dash_useful_components.egg-info/SOURCES.txt
dash_useful_components.egg-info/dependency_links.txt
dash_useful_components.egg-info/top_level.txt