Metadata-Version: 2.1
Name: dash-useful-components
Version: 0.1.0
Summary: Additional useful components for Dash
Home-page: https://github.com/queyruto/dash-useful-components
Author: Olivier Queyrut <oqueyrut@gmail.com>
License: Apache-2.0
Platform: UNKNOWN
Classifier: Framework :: Dash
